overwatch_client/__init__.py
overwatch_client/client.py
overwatch_client/utils.py
overwatch_client/version.py
overwatch_client-0.1.9.dist-info/METADATA
overwatch_client-0.1.9.dist-info/WHEEL
overwatch_client-0.1.9.dist-info/RECORD
