Metadata-Version: 2.1
Name: overwatch-client
Version: 0.1.9
Summary: A python based Overwatch Client for interacting with the overwatch server with higher level apis.
Author: Hamada Gasmallah
Author-email: hamada@distributive.network
Requires-Python: >=3.9,<4.0
Classifier: Programming Language :: Python :: 3
Classifier: Programming Language :: Python :: 3.9
Classifier: Programming Language :: Python :: 3.10
Classifier: Programming Language :: Python :: 3.11
Classifier: Programming Language :: Python :: 3.12
